[
    {
        "id": "حساب_الراتب_1",
        "country": "Algeria",
        "law_domain": "Labor Law",
        "law_name": "قانون العمل الجزاىري",
        "book": "الفصل الخامس: الاجر (الراتب)",
        "title": "طريقة اعداد اجر العامل",
        "article_number": null,
        "classification": {
            "main_category": "اعداد اجر العامل",
            "sub_category": null,
            "section": "الفصل الخامس"
        },
        "text": {
            "original": "طريقة اعداد اجر العامل تمر بعدة خطوات متسلسلة:\n1. تسجيل حضور العامل: يتم اثبات الحضور يدويا (مثل التوقيع) او الكترونيا باستخدام اجهزة ذكية بالبصمة او البطاقة.\n2. تحويل اثبات الحضور: ترسل بيانات الحضور اليومي الى مصلحة المستخدمين او مصلحة المحاسبة حسب التنظيم الداخلي للشركة.\n3. حساب ايام الحضور: يحسب عدد ايام الحضور في الشهر (30 يوما)، مع امكانية بدء الحساب من اي يوم في الشهر، مع الحفاظ على نفس المرجع لكل شهر",
            "language": "ar"
        },
        "text_explanation": "طريقة اعداد اجر العامل تمر بعدة خطوات متسلسلة:\n1. تسجيل حضور العامل: يتم اثبات الحضور يدويا (مثل التوقيع) او الكترونيا باستخدام اجهزة ذكية بالبصمة او البطاقة.\n2. تحويل اثبات الحضور: ترسل بيانات الحضور اليومي الى مصلحة المستخدمين او مصلحة المحاسبة حسب التنظيم الداخلي للشركة.\n3. حساب ايام الحضور: يحسب عدد ايام الحضور في الشهر (30 يوما)، مع امكانية بدء الحساب من اي يوم في الشهر، مع الحفاظ على نفس المرجع لكل شهر",
        "summary": "طريقة اعداد اجر العامل:\n1. تسجيل الحضور يدويا او الكترونيا بالبصمة/البطاقة.\n2. تحويل بيانات الحضور الى مصلحة المستخدمين او المحاسبة.\n3. حساب ايام الحضور الشهرية مع الحفاظ على نفس المرجع لكل شهر",
        "legal_conditions_summary": "",
        "penalties_summary": "",
        "keywords": [
            "اجر العامل",
            "حضور الموظف",
            "حساب الايام",
            "كشف الاجر",
            "الراتب الشهري"
        ],
        "legal_type": "تطبيقية",
        "norm_type": "مكملة",
        "relations": {
            "related_articles": [],
            "derived_from": null,
            "amended_by": null,
            "repeals": null
        },
        "source": {
            "document": "تطبيق عملي",
            "year": 2024,
            "publisher": "مصادر متعددة",
            "links": [
                "https://www.facebook.com/share/p/17r7gJQCYh/?mibextid=wwXIfr"
            ]
        },
        "versioning": {
            "status": "ساري",
            "version": "v1.0",
            "last_update": "2024-06"
        }
    },
    {
        "id": "حساب_الراتب_2",
        "country": "Algeria",
        "law_domain": "Labor Law",
        "law_name": "قانون العمل الجزاىري",
        "book": "الفصل الخامس: الاجر (الراتب)",
        "title": "حساب حقوق و التزامات العامل",
        "article_number": null,
        "classification": {
            "main_category": "حقوق و التزامات العامل",
            "sub_category": null,
            "section": "الفصل الخامس"
        },
        "text": {
            "original": "بالنسبة لحقوق و التزامات العامل:\n- يجب الحرص على الحساب الجيد لحقوق و التزامات العمال للحصول على الدخل الصحيح لكل واحد فيهم حسب سلم الاجور المعمول به في الشركة والمتفق عليه في الاتفاقية الجماعية.\n- التاكد من ايام الحضور والغياب، و الاقتطاعات الضريبية والاجتماعية الدقيقة.\n- في الغالب يتم اعداد نفس الاجرة لكل شهر، غير انه يمكن في بعض الاحيان حساب:\n  - اجور متاخرة \"rappel de salaire\"\n  - منحة نهاية الخدمة \"prime de fin carrière\"\n  - رصيد \"STC\"",
            "language": "ar"
        },
        "text_explanation": "بالنسبة لحقوق و التزامات العامل:\n- يجب الحرص على الحساب الجيد لحقوق و التزامات العمال للحصول على الدخل الصحيح لكل واحد فيهم حسب سلم الاجور المعمول به في الشركة والمتفق عليه في الاتفاقية الجماعية.\n- التاكد من ايام الحضور والغياب، و الاقتطاعات الضريبية والاجتماعية الدقيقة.\n- في الغالب يتم اعداد نفس الاجرة لكل شهر، غير انه يمكن في بعض الاحيان حساب:\n  - اجور متاخرة \"rappel de salaire\"\n  - منحة نهاية الخدمة \"prime de fin carrière\"\n  - رصيد \"STC\"",
        "summary": "حقوق والتزامات العامل: حساب دقيق للاجر حسب سلم الاجور والاتفاقية الجماعية، التحقق من ايام الحضور والغياب والاقتطاعات الضريبية والاجتماعية، وقد تشمل الاجرة المتاخرة (rappel de salaire)، منحة نهاية الخدمة (prime de fin carrière)، ورصيد (STC).",
        "legal_conditions_summary": "",
        "penalties_summary": "",
        "keywords": [
            "حقوق العامل",
            "التزامات العامل",
            "حساب الاجر",
            "الاقتطاعات الضريبية",
            "الاقتطاعات الاجتماعية",
            "rappel de salaire",
            "prime de fin carrière",
            "STC"
        ],
        "legal_type": "تطبيقية",
        "norm_type": "مكملة",
        "relations": {
            "related_articles": [],
            "derived_from": null,
            "amended_by": null,
            "repeals": null
        },
        "source": {
            "document": "تطبيق عملي",
            "year": 2024,
            "publisher": "مصادر متعددة",
            "links": [
                "https://www.facebook.com/share/p/17r7gJQCYh/?mibextid=wwXIfr"
            ]
        },
        "versioning": {
            "status": "ساري",
            "version": "v1.0",
            "last_update": "2024-06"
        }
    },
    {
        "id": "حساب_الراتب_3",
        "country": "Algeria",
        "law_domain": "Labor Law",
        "law_name": "قانون العمل الجزاىري",
        "book": "الفصل الخامس: الاجر (الراتب)",
        "title": "مكونات الاجر",
        "article_number": null,
        "classification": {
            "main_category": "مكونات الاجر",
            "sub_category": null,
            "section": "الفصل الخامس"
        },
        "text": {
            "original": "مكونات الاجر: الاجر الاساسي (salaire de base) المرتبط بالمنصب وسلم الاجور، التعويضات/المنح (les indemnités) مقابل المجهودات والاضرار او مصاريف العمل مثل الطعام والنقل، العلاوات (les primes) مبالغ اضافية للتحفيز او الاداء تصرف عادة فصلية او سنوية، والفواىد (interessement) مبالغ نتيجة تحقيق ارباح خلال السنة حسب فىات العمال وتاثيرهم.",
            "language": "ar"
        },
        "text_explanation": "مكونات الاجر: الاجر الاساسي (salaire de base) المرتبط بالمنصب وسلم الاجور، التعويضات/المنح (les indemnités) مقابل المجهودات والاضرار او مصاريف العمل مثل الطعام والنقل، العلاوات (les primes) مبالغ اضافية للتحفيز او الاداء تصرف عادة فصلية او سنوية، والفواىد (interessement) مبالغ نتيجة تحقيق ارباح خلال السنة حسب فىات العمال وتاثيرهم.",
        "summary": "مكونات الاجر: الاجر الاساسي (salaire de base) المرتبط بالمنصب وسلم الاجور، التعويضات/المنح (les indemnités) مقابل المجهودات والاضرار او مصاريف العمل مثل الطعام والنقل، العلاوات (les primes) مبالغ اضافية للتحفيز او الاداء تصرف عادة فصلية او سنوية، والفواىد (interessement) مبالغ نتيجة تحقيق ارباح خلال السنة حسب فىات العمال وتاثيرهم.",
        "legal_conditions_summary": "",
        "penalties_summary": "",
        "keywords": [
            "مكونات الاجر",
            "الاجر الاساسي",
            "التعويضات",
            "المنح",
            "العلاوات",
            "الفواىد",
            "salaire de base",
            "les indemnites",
            "les primes",
            "interessement"
        ],
        "legal_type": "تطبيقية",
        "norm_type": "مكملة",
        "relations": {
            "related_articles": [],
            "derived_from": null,
            "amended_by": null,
            "repeals": null
        },
        "source": {
            "document": "تطبيق عملي",
            "year": 2024,
            "publisher": "مصادر متعددة",
            "links": [
                "https://www.facebook.com/share/p/17r7gJQCYh/?mibextid=wwXIfr"
            ]
        },
        "versioning": {
            "status": "ساري",
            "version": "v1.0",
            "last_update": "2024-06"
        }
    },
    {
        "id": "حساب_الراتب_4",
        "country": "Algeria",
        "law_domain": "Labor Law",
        "law_name": "قانون العمل الجزاىري",
        "book": "الفصل الخامس: الاجر (الراتب)",
        "title": "حساب الاجر القاعدي",
        "article_number": null,
        "classification": {
            "main_category": "حساب الاجر القاعدي",
            "sub_category": null,
            "section": "الفصل الخامس"
        },
        "text": {
            "original": "حساب الاجر القاعدي :\nمن المعلوم ان عدد ساعات العمل في الاسبوع هو 40 ساعة حسب قانون العمل، و الاجير يحصل على مقابل مالي يتناسب مع الساعات التي عملها خلال الشهر.\nو عملية حسابية بسيطة يمكن حساب عدد ساعات العمل شهريا حسب القاعدة التالية\nساعات العمل في الشهر = (40 ساعة * 52 اسبوع /12 شهرا) = 173.33 ساعة شهريا\nقانون العمل يحدد تقسيم ايام العمل على 05 او 06 ايام حسب تنظيم العمل الداخلي للشركة و يكون الحساب كمايلي :\nفي حالة 05 ايام : ( 05 ايام * 52 اسبوع ) /12 شهر= 21.66 تقرب الى 22 يوما؛\nفي حالة 06 ايام : ) 06 ايام * 52 اسبوع ) /12 شهر = 26 يوما",
            "language": "ar"
        },
        "text_explanation": "حساب الاجر القاعدي :\nمن المعلوم ان عدد ساعات العمل في الاسبوع هو 40 ساعة حسب قانون العمل، و الاجير يحصل على مقابل مالي يتناسب مع الساعات التي عملها خلال الشهر.\nو عملية حسابية بسيطة يمكن حساب عدد ساعات العمل شهريا حسب القاعدة التالية\nساعات العمل في الشهر = (40 ساعة * 52 اسبوع /12 شهرا) = 173.33 ساعة شهريا\nقانون العمل يحدد تقسيم ايام العمل على 05 او 06 ايام حسب تنظيم العمل الداخلي للشركة و يكون الحساب كمايلي :\nفي حالة 05 ايام : ( 05 ايام * 52 اسبوع ) /12 شهر= 21.66 تقرب الى 22 يوما؛\nفي حالة 06 ايام : ) 06 ايام * 52 اسبوع ) /12 شهر = 26 يوما",
        "summary": "حساب الاجر القاعدي :\nمن المعلوم ان عدد ساعات العمل في الاسبوع هو 40 ساعة حسب قانون العمل، و الاجير يحصل على مقابل مالي يتناسب مع الساعات التي عملها خلال الشهر.\nو عملية حسابية بسيطة يمكن حساب عدد ساعات العمل شهريا حسب القاعدة التالية\nساعات العمل في الشهر = (40 ساعة * 52 اسبوع /12 شهرا) = 173.33 ساعة شهريا\nقانون العمل يحدد تقسيم ايام العمل على 05 او 06 ايام حسب تنظيم العمل الداخلي للشركة و يكون الحساب كمايلي :\nفي حالة 05 ايام : ( 05 ايام * 52 اسبوع ) /12 شهر= 21.66 تقرب الى 22 يوما؛\nفي حالة 06 ايام : ) 06 ايام * 52 اسبوع ) /12 شهر = 26 يوما",
        "legal_conditions_summary": "",
        "penalties_summary": "",
        "keywords": [
            "حساب الاجر القاعدي",
            "ساعات العمل الشهرية",
            "تقسيم ايام العمل",
            "قانون العمل",
            "الاجر الشهري"
        ],
        "legal_type": "تطبيقية",
        "norm_type": "مكملة",
        "relations": {
            "related_articles": [],
            "derived_from": null,
            "amended_by": null,
            "repeals": null
        },
        "source": {
            "document": "تطبيق عملي",
            "year": 2024,
            "publisher": "مصادر متعددة",
            "links": [
                "https://www.facebook.com/share/p/17r7gJQCYh/?mibextid=wwXIfr"
            ]
        },
        "versioning": {
            "status": "ساري",
            "version": "v1.0",
            "last_update": "2024-06"
        }
    },
    {
        "id": "حساب_الراتب_5",
        "country": "Algeria",
        "law_domain": "Labor Law",
        "law_name": "قانون العمل الجزاىري",
        "book": "الفصل الخامس: الاجر (الراتب)",
        "title": "حساب التعويضات والعلاوات",
        "article_number": null,
        "classification": {
            "main_category": "حساب التعويضات والعلاوات",
            "sub_category": null,
            "section": "الفصل الخامس"
        },
        "text": {
            "original": "حساب التعويضات و العلاوات :\nهناك نوعان من المنح و العلوات مقسمة حسب كيفية حسابها اما بمعدل مىوي او قيمة ثابتة شهرية\nتعويض الخبرة المهنية = الاجر القاعدي * المعدل (%) * عدد ايام العمل / شهر (22 او 26 يوما).بالنسبة للمنح و العلاوات ذات المعدل فتحسب بدلالة الاجر القاعدي اي كلما زاد الاجر القاعدي ارتفعت المنح و العلاوات  كمثال على ذلك تعويض الخبررة المهنية:\n\n                 او يحسب بعدد الساعات كمايلي:\nتعويض الخبرة المهنية = الاجر القاعدي * المعدل (%) * عدد الساعات العمل / 173.33 ساعة.\nبالنسبة للمنح و العلاوات الثابتة فتحسب حسب ايام العمل مثلا:\nمنحة الاطعام = قيمة المنحة اليومية * عدد الايام العمل ;",
            "language": "ar"
        },
        "text_explanation": "حساب التعويضات و العلاوات :\nهناك نوعان من المنح و العلوات مقسمة حسب كيفية حسابها اما بمعدل مىوي او قيمة ثابتة شهرية\nتعويض الخبرة المهنية = الاجر القاعدي * المعدل (%) * عدد ايام العمل / شهر (22 او 26 يوما).بالنسبة للمنح و العلاوات ذات المعدل فتحسب بدلالة الاجر القاعدي اي كلما زاد الاجر القاعدي ارتفعت المنح و العلاوات  كمثال على ذلك تعويض الخبررة المهنية:\n\n                 او يحسب بعدد الساعات كمايلي:\nتعويض الخبرة المهنية = الاجر القاعدي * المعدل (%) * عدد الساعات العمل / 173.33 ساعة.\nبالنسبة للمنح و العلاوات الثابتة فتحسب حسب ايام العمل مثلا:\nمنحة الاطعام = قيمة المنحة اليومية * عدد الايام العمل ;",
        "summary": "حساب التعويضات والعلاوات:\n\t•\tهناك نوعان: حسب المعدل المىوي او القيمة الثابتة الشهرية.\n\t•\tتعويض الخبرة المهنية:\n\t•\tحسب الايام: الاجر القاعدي × المعدل (%) × عدد ايام العمل / 22 او 26 يوما.\n\t•\tحسب الساعات: الاجر القاعدي × المعدل (%) × عدد ساعات العمل / 173.33 ساعة.\n\t•\tالمنح والعلاوات الثابتة: حسب ايام العمل، مثال: منحة الاطعام = قيمة المنحة اليومية × عدد ايام العمل",
        "legal_conditions_summary": "",
        "penalties_summary": "",
        "keywords": [
            "حساب التعويضات",
            "حساب العلاوات",
            "تعويض الخبرة المهنية",
            "المنح الثابتة",
            "العلاوات الثابتة"
        ],
        "legal_type": "تطبيقية",
        "norm_type": "مكملة",
        "relations": {
            "related_articles": [],
            "derived_from": null,
            "amended_by": null,
            "repeals": null
        },
        "source": {
            "document": "تطبيق عملي",
            "year": 2024,
            "publisher": "مصادر متعددة",
            "links": [
                "https://www.facebook.com/share/p/17r7gJQCYh/?mibextid=wwXIfr"
            ]
        },
        "versioning": {
            "status": "ساري",
            "version": "v1.0",
            "last_update": "2024-06"
        }
    },
    {
        "id": "حساب_الراتب_6",
        "country": "Algeria",
        "law_domain": "Labor Law",
        "law_name": "قانون العمل الجزاىري",
        "book": "الفصل الخامس: الاجر (الراتب)",
        "title": "الاقتطاعات على الاجر",
        "article_number": null,
        "classification": {
            "main_category": "الاقتطاعات على الاجر",
            "sub_category": null,
            "section": "الفصل الخامس"
        },
        "text": {
            "original": "الاقتطاعات على الاجر :\nهناك نوعان من الاقتطاعات تتم على الاجر ضريبة و اجتماعية، حيث ان العامل لن يحصل على كل الاجر الاساسي و المنح و العلاوات.\nاشتراك الضمان الاجتماعي بنسبة 9% من اجر المنصب (مجموع الاجر الاساسي والمنح و العلاوات) ;\nالضريبة على الدخل \"IRG\" حسب جدول الضريبة او 10 % في حالة التعويضات غير شهرية (الاجر المنصب - اقتطاع الضمان الاجتماعي 9%) ;",
            "language": "ar"
        },
        "text_explanation": "الاقتطاعات على الاجر :\nهناك نوعان من الاقتطاعات تتم على الاجر ضريبة و اجتماعية، حيث ان العامل لن يحصل على كل الاجر الاساسي و المنح و العلاوات.\nاشتراك الضمان الاجتماعي بنسبة 9% من اجر المنصب (مجموع الاجر الاساسي والمنح و العلاوات) ;\nالضريبة على الدخل \"IRG\" حسب جدول الضريبة او 10 % في حالة التعويضات غير شهرية (الاجر المنصب - اقتطاع الضمان الاجتماعي 9%) ;",
        "summary": "الاقتطاعات على الاجر:\n\t•\tنوعان: ضريبة واجتماعية، والعامل لا يحصل على كامل الاجر الاساسي والمنح والعلاوات.\n\t•\tاشتراك الضمان الاجتماعي: 9% من مجموع الاجر الاساسي والمنح والعلاوات.\n\t•\tالضريبة على الدخل (IRG): حسب جدول الضريبة او 10% للتعويضات غير الشهرية بعد خصم الضمان الاجتماعي",
        "legal_conditions_summary": "",
        "penalties_summary": "",
        "keywords": [
            "الاقتطاعات على الاجر",
            "اشتراك الضمان الاجتماعي",
            "الضريبة على الدخل",
            "IRG",
            "الاجر الاساسي",
            "المنح",
            "العلاوات"
        ],
        "legal_type": "تطبيقية",
        "norm_type": "مكملة",
        "relations": {
            "related_articles": [],
            "derived_from": null,
            "amended_by": null,
            "repeals": null
        },
        "source": {
            "document": "تطبيق عملي",
            "year": 2024,
            "publisher": "مصادر متعددة",
            "links": [
                "https://www.facebook.com/share/p/17r7gJQCYh/?mibextid=wwXIfr"
            ]
        },
        "versioning": {
            "status": "ساري",
            "version": "v1.0",
            "last_update": "2024-06"
        }
    },
    {
        "id": "حساب_الراتب_7",
        "country": "Algeria",
        "law_domain": "Labor Law",
        "law_name": "قانون العمل الجزاىري",
        "book": "الفصل الخامس: الاجر (الراتب)",
        "title": "اعداد كشف الاجر (bulletin de paie)",
        "article_number": null,
        "classification": {
            "main_category": "اعداد كشف الاجر",
            "sub_category": null,
            "section": "الفصل الخامس"
        },
        "text": {
            "original": "اعداد كشف الاجر (bulletin de paie):\nاعداد كشف الاجر هو اخر مرحلة في عملية حساب الاجر حيث ان المستخدم ملزم بالقانون في تقديم هذه الوثيقة الى العمال كل شهر و تعتبر كدليل لحقوق و الزامات الاجير امام الادارة و القانون .",
            "language": "ar"
        },
        "text_explanation": "اعداد كشف الاجر (bulletin de paie):\nاعداد كشف الاجر هو اخر مرحلة في عملية حساب الاجر حيث ان المستخدم ملزم بالقانون في تقديم هذه الوثيقة الى العمال كل شهر و تعتبر كدليل لحقوق و الزامات الاجير امام الادارة و القانون .",
        "summary": "اعداد كشف الاجر (bulletin de paie):\n\t•\tاخر مرحلة في حساب الاجر.\n\t•\tالزام قانوني لصاحب العمل بتقديمه شهريا.\n\t•\tيعتبر دليلا على حقوق والتزامات الاجير امام الادارة والقانون",
        "legal_conditions_summary": "",
        "penalties_summary": "",
        "keywords": [
            "كشف الاجر",
            "bulletin de paie",
            "حقوق الاجير",
            "التزامات الاجير",
            "اعداد كشف الاجر"
        ],
        "legal_type": "تطبيقية",
        "norm_type": "مكملة",
        "relations": {
            "related_articles": [],
            "derived_from": null,
            "amended_by": null,
            "repeals": null
        },
        "source": {
            "document": "تطبيق عملي",
            "year": 2024,
            "publisher": "مصادر متعددة",
            "links": [
                "https://www.facebook.com/share/p/17r7gJQCYh/?mibextid=wwXIfr"
            ]
        },
        "versioning": {
            "status": "ساري",
            "version": "v1.0",
            "last_update": "2024-06"
        }
    },
    {
        "id": "DZ_LABOR_ART_10",
        "country": "Algeria",
        "law_domain": "Labor Law",
        "law_name": "قانون 90-11 المتعلق بعلاقات العمل",
        "book": "الباب الثاني: عقد العمل الفردي",
        "title": "إثبات علاقة العمل (ماذا أفعل إذا لم أحصل على عقد؟)",
        "article_number": 10,
        "classification": { "main_category": "علاقات العمل", "sub_category": "عقد العمل", "section": "إثبات العقد" },
        "text": {
            "original": "المادة 10 : تعتبر علاقة العمل قائمة بين العامل والمستخدم بمجرد تنفيذ العمل، حتى في غياب عقد مكتوب، ما لم يثبت خلاف ذلك بكل الوسائل.",
            "language": "ar"
        },
        "text_explanation": "هذه المادة هي حماية لكل عامل يشتغل 'بلاكارت' أو بدون عقد مكتوب. القانون الجزائري يقول: بمجرد أنك تعمل وتتقاضى أجراً، فأنت محمي قانوناً وتعتبر صاحب 'عقد غير محدد المدة' (CDI). يمكنك إثبات عملك بشهادة الشهود أو أي وثيقة، ولا يحتاج الأمر لورقة رسمية لكي تطلب حقوقك.",
        "summary": "المادة 10 - إقرار قيام علاقة العمل بمجرد ممارسة النشاط الفعلي حتى في حال انعدام العقد المكتوب.",
        "legal_conditions_summary": "1. تنفيذ العمل لصالح المستخدم. 2. تقاضي أجر. 3. إمكانية الإثبات بكل الوسائل (شهود، صور، رسائل).",
        "penalties_summary": null,
        "keywords": ["ماعنديش كونطرا", "خدمة بدون عقد", "إثبات العمل", "عقد شفهي في العمل", "حقوق العامل بدون أوراق", "مانيش مسوري"],
        "legal_type": "جوهري / حمائي",
        "norm_type": "آمرة",
        "relations": { "related_articles": [11, 12], "derived_from": null, "amended_by": null, "repeals": null },
        "source": { "document": "الجريدة الرسمية", "year": 1990, "publisher": "وزارة العمل" },
        "versioning": { "status": "ساري", "version": "v1.0", "last_update": "1990-04-21" }
    },
    {
        "id": "DZ_LABOR_ART_73_4",
        "country": "Algeria",
        "law_domain": "Labor Law",
        "law_name": "قانون 90-11 المتعلق بعلاقات العمل",
        "book": "الباب السادس: إنهاء علاقة العمل",
        "title": "التعويض عن التسريح التعسفي (الطرد بدون سبب)",
        "article_number": "73-4",
        "classification": { "main_category": "إنهاء العمل", "sub_category": "الطرد التعسفي", "section": "التعويضات" },
        "text": {
            "original": "المادة 73-4 : إذا وقع تسريح العامل خرقا للإجراءات القانونية أو بدون سبب جدي، تقضي المحكمة المختصة بإعادة إدماج العامل في المؤسسة مع الحفاظ على حقوقه، أو تمنح له تعويضاً مالياً لا يقل عن أجر ستة (6) أشهر.",
            "language": "ar"
        },
        "text_explanation": "إذا طردك صاحب العمل 'بدون سبب' أو 'ظلماً'، ترفع قضية في القسم الاجتماعي. القاضي سيحكم لك إما بالعودة للعمل أو بمنحك تعويض مالي كبير (على الأقل خلصت 6 أشهر). هذه هي المادة التي تحمي العمال من 'البريستيج' أو الطرد المفاجئ.",
        "summary": "المادة 73-4 - تقرير حق العامل في التعويض المالي (6 أشهر كحد أدنى) أو إعادة الإدماج في حالة الطرد التعسفي.",
        "legal_conditions_summary": "1. وقوع طرد بدون سبب مهني جسيم. 2. عدم احترام إجراءات التأديب. 3. صدور حكم قضائي.",
        "penalties_summary": "إلزام المستخدم بدفع تعويضات مالية للعامل.",
        "keywords": ["طردوني بدون سبب", "طرد تعسفي", "تعويض الطرد", "حقوقي عند الطرد", "نهاية الخدمة", "تسريح العمال","طردوني بدون سبب", "licenciement abusif", "تعويض الفصل", "قضية طرد"],
        "legal_type": "حمائي / مالي",
        "norm_type": "آمرة",
        "relations": { "related_articles": [73], "derived_from": null, "amended_by": "القانون 91-29", "repeals": null },
        "source": { "document": "الجريدة الرسمية", "year": 1990, "publisher": "وزارة العمل" },
        "versioning": { "status": "ساري", "version": "v1.0", "last_update": "1991-12-21" }
    },
    {
        "id": "DZ_LABOR_ART_147",
        "country": "Algeria",
        "law_domain": "Labor Law",
        "law_name": "قانون 90-11 المتعلق بعلاقات العمل",
        "book": "أجهزة المراقبة والنزاعات",
        "title": "شكوى لمفتشية العمل (الصلح والرقابة)",
        "article_number": 147,
        "classification": { "main_category": "الرقابة", "sub_category": "مفتشية العمل", "section": "المنازعات" },
        "text": {
            "original": "المادة 147 : (مستخلصة) تضطلع مفتشية العمل بمهمة الرقابة والمصالحة في نزاعات العمل الفردية والجماعية. يجب على العامل اللجوء لمفتشية العمل للقيام بمحاولة الصلح قبل الذهاب للقضاء.",
            "language": "ar"
        },
        "text_explanation": "إذا تعرضت للظلم، 'لانسبكتور دو ترافاي' (مفتشية العمل) هي وجهتك الأولى. المفتش سيستدعي صاحب العمل لمحاولة حل المشكلة ودياً (الصلح). إذا فشل الصلح، يعطيك 'محضر عدم صلح' لكي ترفع به قضية في المحكمة.",
        "summary": "المادة 147 - وجوب اللجوء لمفتشية العمل لإجراء محاولة الصلح الإجبارية قبل التقاضي في مسائل العمل.",
        "legal_conditions_summary": "تقديم شكوى مكتوبة + حضور جلسة المصالحة.",
        "penalties_summary": null,
        "keywords": ["شكوى لمفتش العمل", "مفتشية العمل", "حقوقي ضاعت", "نصبت على المستخدم", "محضر عدم صلح","inspection du travail","وين نشكي من صاحب العمل","مشكلة مع المستخدم","رب العمل ظلمني"],
        "legal_type": "إجرائية",
        "norm_type": "آمرة",
        "relations": { "related_articles": [148, 149], "derived_from": null, "amended_by": null, "repeals": null },
        "source": { "document": "الجريدة الرسمية", "year": 1990, "publisher": "وزارة العمل" },
        "versioning": { "status": "ساري", "version": "v1.0", "last_update": "1990-04-21" }
    }
]